<?xml version="1.0" encoding="utf-8"?>
<resources>

    <!-- tc-size-margin -->
    <dimen name="tc_margin_large_30">30dp</dimen>
    <dimen name="tc_margin_large">25dp</dimen>
    <dimen name="tc_margin_big">20dp</dimen>
    <dimen name="tc_margin_normal">16dp</dimen>
    <dimen name="tc_margin_small">10dp</dimen>
    <dimen name="tc_margin_mini">5dp</dimen>
    <dimen name="tc_margin_mini_2">2dp</dimen>

    <!-- tc-size-text -->
    <dimen name="tc_text_size_large_20">20sp</dimen>
    <dimen name="tc_text_size_large">18sp</dimen>
    <dimen name="tc_text_size_big">16sp</dimen>
    <dimen name="tc_text_size_normal">14sp</dimen>
    <dimen name="tc_text_size_small">12sp</dimen>
    <dimen name="tc_text_size_mini">10sp</dimen>
    <dimen name="tc_text_size_mini_8">8sp</dimen>

    <!-- tc-other -->
    <dimen name="tc_menu_min_width">48dp</dimen>

    <!-- menu_item -->
    <dimen name="menu_item_padding_bottom">10dp</dimen>
    <dimen name="menu_item_padding_left">20dp</dimen>
    <dimen name="menu_item_padding_right">20dp</dimen>
    <dimen name="menu_item_padding_top">10dp</dimen>

    <!-- **************** project **************** -->

</resources>